aelklog/__init__.py
aelklog/aelklog.py
aelklog-0.1.1.dist-info/licenses/LICENSE
aelklog-0.1.1.dist-info/METADATA
aelklog-0.1.1.dist-info/WHEEL
aelklog-0.1.1.dist-info/top_level.txt
aelklog-0.1.1.dist-info/RECORD
