Metadata-Version: 2.4
Name: aelklog
Version: 0.1.1
Summary: A simple logging package that sends logs asynchronously to ELK with customizable fields.
Author-email: "H.Yang" <yeticry@gmail.com>
Project-URL: Homepage, https://github.com/hoyang/aelklog
Project-URL: Repository, https://github.com/hoyang/aelklog
Requires-Python: >=3.8
License-File: LICENSE
Requires-Dist: python-dotenv>=1.0.0
Dynamic: license-file
